{
  "name": "wasmcbind",
  "version": "0.1.1",
  "description": "Wasmcbind is a C project that offers bindings to Web APIs for use with wasm.",
  "homepage": "https://github.com/emlite/wasmcbind",
  "license": "MIT",
  "dependencies": [
    {
      "name": "emlite",
      "features": [
        "capi"
      ]
    },
    {
      "name": "vcpkg-cmake",
      "host": true
    },
    {
      "name": "vcpkg-cmake-config",
      "host": true
    }
  ],
  "features": {
    "webbind": {
      "description": "Build/install the webbind library"
    }
  }
}
